README.md
setup.py
cobweb/__init__.py
cobweb/defaults.py
cobweb/scripts.py
cobweb/settings.py
cobweb/adapters/__init__.py
cobweb/adapters/dynamic_http.py
cobweb/adapters/file.py
cobweb/adapters/http.py
cobweb/adapters/image.py
cobweb/adapters/session.py
cobweb/bbs/__init__.py
cobweb/bbs/user_agents.txt
cobweb/helpers/__init__.py
cobweb/link_extractor/__init__.py
cobweb/link_extractor/bloom_filter.py
cobweb/spiders/__init__.py
cobweb_scrapper.egg-info/PKG-INFO
cobweb_scrapper.egg-info/SOURCES.txt
cobweb_scrapper.egg-info/dependency_links.txt
cobweb_scrapper.egg-info/entry_points.txt
cobweb_scrapper.egg-info/top_level.txt